cancer_api/__init__.py
cancer_api/annotations.py
cancer_api/base.py
cancer_api/connections.py
cancer_api/effects.py
cancer_api/exceptions.py
cancer_api/files.py
cancer_api/metadata.py
cancer_api/misc.py
cancer_api/mutations.py
cancer_api/parsers.py
cancer_api/utils.py
cancer_api-0.2.4.dist-info/top_level.txt
cancer_api-0.2.4.dist-info/METADATA
cancer_api-0.2.4.dist-info/DESCRIPTION.rst
cancer_api-0.2.4.dist-info/metadata.json
cancer_api-0.2.4.dist-info/WHEEL
cancer_api-0.2.4.dist-info/RECORD
