Metadata-Version: 2.0
Name: cancer-api
Version: 0.2.4
Summary: A Python framework and API for handling and storing cancer genomics data and metadata.
Home-page: https://github.com/brunogrande/cancer_api
Author: Bruno Grande
Author-email: bgrande@sfu.ca
License: MIT
Keywords: bioinformatics cancer genomics framework api
Platform: UNKNOWN
Classifier: Programming Language :: Python :: 2 :: Only
Classifier: Programming Language :: Python :: 2.7
Classifier: Development Status :: 3 - Alpha
Classifier: Intended Audience :: Science/Research
Classifier: Topic :: Scientific/Engineering :: Bio-Informatics
Classifier: License :: OSI Approved :: MIT License
Requires-Dist: SQLAlchemy (>=0.9.8)
